{"name":"\n        [DBD-Raws][4K_HDR][指环王3：王者归来/魔戒3/The Lord of the Rings: The Return of the King][加长版][2160P][BDRip][HEVC-10bit][中英外挂][THD][MKV]","workName":"","source":"Blu-ray","resolution":"1080p","subtitleProvider":"","url":"http://www.kisssub.org/show-0e3129ace1b6dd6ae45b775a8ab3f8f6b2e75870.html","isNew":true,"publishTime":"2021-09-14T16:23:14.000Z","isComplete":false,"generalRanking":3,"magnetLink":"magnet:?xt=urn:btih:0e3129ace1b6dd6ae45b775a8ab3f8f6b2e75870&tr=http://open.acgtracker.com:1096/announce"}